<annotation>
	<folder></folder>
	<filename>135994133_4f306fe4bf_n_jpg.rf.c3eb748370d68069e96862740dce0b4d.jpg</filename>
	<path>135994133_4f306fe4bf_n_jpg.rf.c3eb748370d68069e96862740dce0b4d.jpg</path>
	<source>
		<database>roboflow.ai</database>
	</source>
	<size>
		<width>416</width>
		<height>416</height>
		<depth>3</depth>
	</size>
	<segmented>0</segmented>
	<object>
		<name>TULIP</name>
		<pose>Unspecified</pose>
		<truncated>0</truncated>
		<difficult>0</difficult>
		<occluded>0</occluded>
		<bndbox>
			<xmin>59</xmin>
			<xmax>343</xmax>
			<ymin>12</ymin>
			<ymax>400</ymax>
		</bndbox>
	</object>
</annotation>
